plotlywrapper.py
plotlywrapper-0.1.0.dist-info/LICENSE
plotlywrapper-0.1.0.dist-info/WHEEL
plotlywrapper-0.1.0.dist-info/METADATA
plotlywrapper-0.1.0.dist-info/RECORD
