Metadata-Version: 2.1
Name: plotlywrapper
Version: 0.1.0
Summary: Plotlywrapper: to make easy plots easy to make.
Home-page: https://github.com/jwkvam/plotlywrapper
License: UNKNOWN
Keywords: plotly chart visualization interactive
Author: Jacques Kvam
Author-email: jwkvam+pypi@gmail.com
Requires-Python: >=3.5
Classifier: License :: OSI Approved :: MIT License
Classifier: Programming Language :: Python :: 3
Classifier: Programming Language :: Python :: 3.5
Classifier: Programming Language :: Python :: 3.6
Classifier: Programming Language :: Python :: 3.7
Requires-Dist: plotly (>=3.0.0)
Requires-Dist: numpy
Requires-Dist: pandas (>=0.23.0)
